sedeprot.py
sedeprot-1.0.0.dist-info/DESCRIPTION.rst
sedeprot-1.0.0.dist-info/METADATA
sedeprot-1.0.0.dist-info/RECORD
sedeprot-1.0.0.dist-info/WHEEL
sedeprot-1.0.0.dist-info/metadata.json
sedeprot-1.0.0.dist-info/top_level.txt
