Metadata-Version: 2.0
Name: sedeprot
Version: 1.0.0
Summary: A self-enforcing protocol for collaborative decision-making
Home-page: https://github.com/buckket/sedeprot
Author: buckket
Author-email: buckket@cock.li
License: GPLv3+
Platform: any
Provides-Extra: dev
Requires-Dist: pytest; extra == 'dev'
Requires-Dist: pytest-cov; extra == 'dev'
Requires-Dist: tox; extra == 'dev'
